gsmm/__init__.py
gsmm/csm/__init__.py
gsmm/csm/analyse_csm.py
gsmm/csm/build_csm.py
gsmm/csm/config.py
gsmm/csm/visualisation.py
gsmm-0.1.9.dist-info/LICENSE.txt
gsmm-0.1.9.dist-info/METADATA
gsmm-0.1.9.dist-info/WHEEL
gsmm-0.1.9.dist-info/top_level.txt
gsmm-0.1.9.dist-info/RECORD
