Metadata-Version: 2.1
Name: gsmm
Version: 0.1.9
Summary: Genome Scale Metabolic Modeling - [Currently] Pipeline for building and analyzing context-specific metabolic models
Home-page: https://github.com/KarthikDani/PHCCOProject/tree/main/gsmm
Author: Karthik Dani
Author-email: karthikdani14@gmail.com
License: MIT
Classifier: Development Status :: 3 - Alpha
Classifier: Programming Language :: Python :: 3
Classifier: License :: OSI Approved :: MIT License
Classifier: Operating System :: OS Independent
Classifier: Intended Audience :: Science/Research
Classifier: Topic :: Scientific/Engineering :: Bio-Informatics
Requires-Python: >=3.7
License-File: LICENSE.txt
Requires-Dist: numpy
Requires-Dist: pandas
Requires-Dist: seaborn
Requires-Dist: matplotlib
Requires-Dist: cobra
Requires-Dist: corda
Requires-Dist: scipy
Requires-Dist: scikit-learn
